mrs_inspector/__init__.py
mrs_inspector/cli.py
mrs_inspector/graph.py
mrs_inspector/graph_builder.py
mrs_inspector/inspector.py
mrs_inspector/state.py
mrs_inspector/tracer.py
mrs_inspector/tree_view.py
mrs_inspector/utils.py
mrs_inspector/validator.py
mrs_inspector/version.py
mrs_inspector-1.0.0.dist-info/licenses/LICENSE
mrs_inspector-1.0.0.dist-info/licenses/NOTICE
mrs_inspector-1.0.0.dist-info/METADATA
mrs_inspector-1.0.0.dist-info/WHEEL
mrs_inspector-1.0.0.dist-info/top_level.txt
mrs_inspector-1.0.0.dist-info/RECORD
