Metadata-Version: 2.4
Name: mrs_inspector
Version: 1.0.0
Summary: A lightweight tracing and reasoning-structure capture utility.
Author-email: RJ Sabouhi <rjsabouhi@gmail.com>
Project-URL: Homepage, https://rjsabouhi.github.io/mrs-inspector/
Project-URL: Documentation, https://rjsabouhi.github.io/mrs-inspector/
Project-URL: Repository, https://github.com/rjsabouhi/mrs-inspector
Keywords: tracing,inspection,debugging,reasoning,analysis
Requires-Python: >=3.9
License-File: LICENSE
License-File: NOTICE
Requires-Dist: networkx>=3.0
Requires-Dist: matplotlib>=3.5
Dynamic: license-file
